brainframe/api/__init__.py
brainframe/api/bf_codecs/__init__.py
brainframe/api/bf_codecs/alarm_codecs.py
brainframe/api/bf_codecs/base_codecs.py
brainframe/api/bf_codecs/capsule_codecs.py
brainframe/api/bf_codecs/cloud_codecs.py
brainframe/api/bf_codecs/condition_codecs.py
brainframe/api/bf_codecs/config_codecs.py
brainframe/api/bf_codecs/detection_codecs.py
brainframe/api/bf_codecs/identity_codecs.py
brainframe/api/bf_codecs/image_utils.py
brainframe/api/bf_codecs/license_codecs.py
brainframe/api/bf_codecs/oauth2_codecs.py
brainframe/api/bf_codecs/premises_codecs.py
brainframe/api/bf_codecs/sorting.py
brainframe/api/bf_codecs/user_codecs.py
brainframe/api/bf_codecs/zone_codecs.py
brainframe/api/bf_errors.py
brainframe/api/status_receiver.py
brainframe/api/stub.py
brainframe/api/stubs/__init__.py
brainframe/api/stubs/alarms.py
brainframe/api/stubs/alerts.py
brainframe/api/stubs/analysis.py
brainframe/api/stubs/base_stub.py
brainframe/api/stubs/capsules.py
brainframe/api/stubs/cloud_tokens.py
brainframe/api/stubs/cloud_users.py
brainframe/api/stubs/encodings.py
brainframe/api/stubs/identities.py
brainframe/api/stubs/licenses.py
brainframe/api/stubs/oauth2.py
brainframe/api/stubs/premises.py
brainframe/api/stubs/process_image.py
brainframe/api/stubs/storage.py
brainframe/api/stubs/streams.py
brainframe/api/stubs/users.py
brainframe/api/stubs/zone_statuses.py
brainframe/api/stubs/zones.py
brainframe_api-0.30.4.dist-info/COPYING
brainframe_api-0.30.4.dist-info/METADATA
brainframe_api-0.30.4.dist-info/WHEEL
brainframe_api-0.30.4.dist-info/RECORD
