Metadata-Version: 2.1
Name: brainframe-api
Version: 0.30.4
Summary: Provides a Python wrapper around the BrainFrame REST API.
Home-page: https://github.com/aotuai/brainframe_python
License: BSD-3-Clause
Author: Aotu
Requires-Python: >=3.6,<4.0
Classifier: License :: OSI Approved :: BSD License
Classifier: Programming Language :: Python :: 3
Classifier: Programming Language :: Python :: 3.6
Classifier: Programming Language :: Python :: 3.7
Classifier: Programming Language :: Python :: 3.8
Classifier: Programming Language :: Python :: 3.9
Classifier: Programming Language :: Python :: 3.10
Classifier: Programming Language :: Python :: 3.11
Classifier: Programming Language :: Python :: 3.12
Classifier: Topic :: Scientific/Engineering :: Artificial Intelligence
Requires-Dist: dataclasses (>=0.7,<0.8) ; python_version >= "3.6" and python_version < "3.7"
Requires-Dist: numpy (>=1.16,<2.0)
Requires-Dist: pillow (>=7.0.0)
Requires-Dist: requests (>=2.24.0,<3.0.0)
Project-URL: Documentation, https://brainframe-python-api.readthedocs.io/en/latest/
